rusmppyc-0.3.0a4.dist-info/METADATA
rusmppyc-0.3.0a4.dist-info/WHEEL
rusmppyc/__init__.py
rusmppyc/__init__.pyi
rusmppyc/client.py
rusmppyc/client.pyi
rusmppyc/events.py
rusmppyc/events.pyi
rusmppyc/exceptions.py
rusmppyc/exceptions.pyi
rusmppyc/py.typed
rusmppyc/rusmppyc.cpython-312-x86_64-linux-gnu.so
rusmppyc/rusmppyc.py
rusmppyc/rusmppyc.pyi
rusmppyc-0.3.0a4.dist-info/RECORD
