Metadata-Version: 2.4
Name: rusmppyc
Version: 0.3.0a4
Classifier: Programming Language :: Rust
Classifier: Programming Language :: Python :: Implementation :: CPython
Classifier: Programming Language :: Python :: Implementation :: PyPy
Summary: An async SMPP v5 Python client powered by Rust
Keywords: smpp,smsc,messaging,networking,protocol
Author-email: "Jad K. Haddad" <jadkhaddad@gmail.com>
Maintainer-email: "Jad K. Haddad" <jadkhaddad@gmail.com>
License: MIT OR Apache-2.0
Requires-Python: >=3.8
Project-URL: Homepage, https://github.com/Rusmpp/Rusmpp
Project-URL: Repository, https://github.com/Rusmpp/Rusmpp.git
